snappy2/Snappy2.py
snappy2/__init__.py
snappy2/controls/Detector.py
snappy2/controls/FacePainter.py
snappy2/controls/Generate.py
snappy2/controls/__init__.py
snappy2/resource/.DS_Store
snappy2/resource/example/.DS_Store
snappy2/resource/example/arch.png
snappy2/resource/example/ears_on_face.PNG
snappy2/resource/example/people_cover.png
snappy2/resource/example/tony_glasses.PNG
snappy2/resource/example/tony_mustache.PNG
snappy2/resource/font/.DS_Store
snappy2/resource/font/Asap-Bold.ttf
snappy2/resource/font/OFL.txt
snappy2/resource/haarcascades/.DS_Store
snappy2/resource/haarcascades/haarcascade_frontalface_default.xml
snappy2/resource/images/overlay/.DS_Store
snappy2/resource/images/overlay/ears_bear.png
snappy2/resource/images/overlay/ears_cat.png
snappy2/resource/images/overlay/ears_teady.png
snappy2/resource/images/overlay/hat1.png
snappy2/resource/images/overlay/hat2.png
snappy2/resource/images/overlay/mus1.png
snappy2/resource/images/overlay/mus2.png
snappy2/resource/images/overlay/mus3.png
snappy2/resource/images/overlay/sunglasses1.png
snappy2/resource/images/overlay/sunglasses2.png
snappy2/resource/images/test_images/.DS_Store
snappy2/resource/images/test_images/front_face.jpg
snappy2/resource/images/test_images/side_face.jpg
snappy2/resource/models/.DS_Store
snappy2/resource/models/keras_cv_base_model_1_avg.h5
snappy2/utils/Constants.py
snappy2/utils/Utility.py
snappy2/utils/__init__.py
snappy2-0.4.data/data/snappy2/resource/.DS_Store
snappy2-0.4.data/data/snappy2/resource/Asap-Bold.ttf
snappy2-0.4.data/data/snappy2/resource/OFL.txt
snappy2-0.4.data/data/snappy2/resource/arch.png
snappy2-0.4.data/data/snappy2/resource/ears_bear.png
snappy2-0.4.data/data/snappy2/resource/ears_cat.png
snappy2-0.4.data/data/snappy2/resource/ears_on_face.PNG
snappy2-0.4.data/data/snappy2/resource/ears_teady.png
snappy2-0.4.data/data/snappy2/resource/front_face.jpg
snappy2-0.4.data/data/snappy2/resource/haarcascade_frontalface_default.xml
snappy2-0.4.dist-info/LICENSE
snappy2-0.4.dist-info/METADATA
snappy2-0.4.dist-info/WHEEL
snappy2-0.4.dist-info/top_level.txt
snappy2-0.4.dist-info/RECORD
