Metadata-Version: 2.1
Name: snappy2
Version: 0.4
Summary: Detect faces and draw overlay images
Home-page: https://snappy2.ahmadai.com/
Author: Albarqawi
License-File: LICENSE
Requires-Dist: opencv-python ==3.4.18.65
Requires-Dist: Pillow ==9.4.0
Requires-Dist: tensorflow ==2.9.0
Requires-Dist: keras ==2.9.0
Requires-Dist: numpy ==1.24.1
Requires-Dist: Markdown ==3.4.1
Requires-Dist: absl-py ==1.4.0
Requires-Dist: Werkzeug ==2.2.2
Requires-Dist: h5py ==3.1.0
Requires-Dist: intelli ==0.0.8
